yolox/__init__.py
yolox/cli/__init__.py
yolox/cli/__main__.py
yolox/cli/demo.py
yolox/cli/eval.py
yolox/cli/export_onnx.py
yolox/cli/export_torchscript.py
yolox/cli/train.py
yolox/cli/trt.py
yolox/cli/utils.py
yolox/cli/visualize_assign.py
yolox/config.py
yolox/core/__init__.py
yolox/core/launch.py
yolox/core/trainer.py
yolox/data/__init__.py
yolox/data/data_augment.py
yolox/data/data_prefetcher.py
yolox/data/dataloading.py
yolox/data/datasets/__init__.py
yolox/data/datasets/coco.py
yolox/data/datasets/coco_classes.py
yolox/data/datasets/datasets_wrapper.py
yolox/data/datasets/mosaicdetection.py
yolox/data/datasets/voc.py
yolox/data/datasets/voc_classes.py
yolox/data/samplers.py
yolox/evaluators/__init__.py
yolox/evaluators/coco_evaluator.py
yolox/evaluators/voc_eval.py
yolox/evaluators/voc_evaluator.py
yolox/layers/__init__.py
yolox/layers/cocoeval/cocoeval.cpp
yolox/layers/cocoeval/cocoeval.h
yolox/layers/fast_coco_eval_api.py
yolox/layers/jit_ops.py
yolox/models/__init__.py
yolox/models/build.py
yolox/models/darknet.py
yolox/models/losses.py
yolox/models/network_blocks.py
yolox/models/processor.py
yolox/models/yolo_fpn.py
yolox/models/yolo_head.py
yolox/models/yolo_pafpn.py
yolox/models/yolox.py
yolox/utils/__init__.py
yolox/utils/allreduce_norm.py
yolox/utils/boxes.py
yolox/utils/checkpoint.py
yolox/utils/compat.py
yolox/utils/demo_utils.py
yolox/utils/dist.py
yolox/utils/ema.py
yolox/utils/logger.py
yolox/utils/lr_scheduler.py
yolox/utils/metric.py
yolox/utils/mlflow_logger.py
yolox/utils/model_utils.py
yolox/utils/setup_env.py
yolox/utils/visualize.py
pixeltable_yolox-0.4.2.dist-info/LICENSE
pixeltable_yolox-0.4.2.dist-info/METADATA
pixeltable_yolox-0.4.2.dist-info/WHEEL
pixeltable_yolox-0.4.2.dist-info/entry_points.txt
pixeltable_yolox-0.4.2.dist-info/RECORD
