Metadata-Version: 2.3
Name: pixeltable-yolox
Version: 0.4.2
Summary: Lightweight, open-source, high-performance Yolo implementation
License: Apache-2.0
Author: Pixeltable, Inc.
Author-email: contact@pixeltable.com>
Requires-Python: >=3.9,<4.0
Classifier: Intended Audience :: Developers
Classifier: Intended Audience :: Science/Research
Classifier: License :: OSI Approved :: Apache Software License
Classifier: Operating System :: MacOS
Classifier: Operating System :: Microsoft :: Windows
Classifier: Operating System :: POSIX :: Linux
Classifier: Programming Language :: Python :: 3.9
Classifier: Programming Language :: Python :: 3.10
Classifier: Programming Language :: Python :: 3.11
Classifier: Programming Language :: Python :: 3.12
Classifier: Programming Language :: Python :: 3.13
Classifier: Topic :: Scientific/Engineering :: Artificial Intelligence
Classifier: Topic :: Software Development :: Libraries :: Python Modules
Requires-Dist: loguru (>=0.7.2)
Requires-Dist: ninja (>=1.11.1.1)
Requires-Dist: numpy (>=1.26.4)
Requires-Dist: onnx (>=1.17.0)
Requires-Dist: onnxsim (>=0.4.10)
Requires-Dist: opencv-python (>=4.10.0.84)
Requires-Dist: psutil (>=5.9.7)
Requires-Dist: pycocotools (>=2.0.7)
Requires-Dist: tabulate (>=0.9.0)
Requires-Dist: tensorboard (>=2.18.0)
Requires-Dist: thop (>=0.1.1.post2209072238)
Requires-Dist: torch (>=2.2.2)
Requires-Dist: torchvision (>=0.17.2)
Requires-Dist: tqdm (>=4.67.1)
Project-URL: Repository, https://github.com/pixeltable/pixeltable-yolox
